README.md
setup.py
ptcaffe/__init__.py
ptcaffe/a.py
ptcaffe/caffenet.py
ptcaffe/deploynet.py
ptcaffe/layer_dict.py
ptcaffe.egg-info/PKG-INFO
ptcaffe.egg-info/SOURCES.txt
ptcaffe.egg-info/dependency_links.txt
ptcaffe.egg-info/entry_points.txt
ptcaffe.egg-info/requires.txt
ptcaffe.egg-info/top_level.txt
ptcaffe/converter/__init__.py
ptcaffe/converter/caffe2ptcaffe.py
ptcaffe/converter/darknet2ptcaffe.py
ptcaffe/converter/onnx2ptcaffe.py
ptcaffe/converter/ptcaffe2caffe.py
ptcaffe/converter/ptcaffe2darknet.py
ptcaffe/converter/ptcaffe2onnx.py
ptcaffe/converter/ptcaffe2tensorrt.py
ptcaffe/converter/pytorch2ptcaffe.py
ptcaffe/converter/tensorflow2ptcaffe.py
ptcaffe/layers/__init__.py
ptcaffe/layers/activation_layers.py
ptcaffe/layers/auxiliary_layers.py
ptcaffe/layers/caffe_data.py
ptcaffe/layers/comm_layers.py
ptcaffe/layers/container_layers.py
ptcaffe/layers/convolution_layers.py
ptcaffe/layers/dropout_layers.py
ptcaffe/layers/evaluation_layers.py
ptcaffe/layers/evaluation_metrics.py
ptcaffe/layers/linear_layers.py
ptcaffe/layers/loss_layers.py
ptcaffe/layers/normalization_layers.py
ptcaffe/layers/pooling_layers.py
ptcaffe/layers/quantization_layers.py
ptcaffe/layers/recurrent_layers.py
ptcaffe/layers/ssd_layers.py
ptcaffe/layers/utility_layers.py
ptcaffe/layers/data_layers/__init__.py
ptcaffe/layers/data_layers/base_data_layer.py
ptcaffe/layers/data_layers/folder_data_layer.py
ptcaffe/layers/data_layers/hdf5_data_layer.py
ptcaffe/layers/data_layers/image_cropping_layer.py
ptcaffe/layers/data_layers/image_data_layer.py
ptcaffe/layers/data_layers/imagenet_data_layer.py
ptcaffe/layers/data_layers/input_data_layer.py
ptcaffe/layers/data_layers/list_data_layer.py
ptcaffe/layers/data_layers/lmdb_data_layer.py
ptcaffe/layers/data_layers/mnist_data_layer.py
ptcaffe/layers/data_layers/pickle_data_layer.py
ptcaffe/layers/data_layers/random_data_layer.py
ptcaffe/layers/data_layers/torchvision_data_layer.py
ptcaffe/layers/pytorch_layers/__init__.py
ptcaffe/layers/pytorch_layers/convolution_layers.py
ptcaffe/layers/pytorch_layers/pooling_layers.py
ptcaffe/layers/pytorch_layers/sparse_layers.py
ptcaffe/models/__init__.py
ptcaffe/models/alexnet.py
