Metadata-Version: 1.0
Name: ptcaffe
Version: 1.1
Summary: pytorch caffe
Home-page: http://github.com/orion/ptcaffe
Author: xiaohang
Author-email: xiaohang@ainirobot.com
License: MIT Licence
Platform: any
